globalmart_api/__init__.py
globalmart_api/process_json.py
globamart_api-0.1.dist-info/License.txt
globamart_api-0.1.dist-info/METADATA
globamart_api-0.1.dist-info/WHEEL
globamart_api-0.1.dist-info/top_level.txt
globamart_api-0.1.dist-info/RECORD
